{
  "run_id": "RUN_20260204_234342_996d5a3920e1",
  "timestamp": "2026-02-05T05:16:40.325477",
  "document": "Ellis-Van-Creveld-Syndrome.pdf",
  "document_path": "/Users/frederictetard/Projects/ese/gold_data/NLP4RARE/train/Ellis-Van-Creveld-Syndrome.pdf",
  "pipeline_version": "0.8",
  "total_candidates": 7,
  "total_validated": 7,
  "total_rejected": 0,
  "total_ambiguous": 0,
  "diseases": [
    {
      "matched_text": "Ellis-Van Creveld syndrome",
      "preferred_label": "Ellis-VAN Creveld syndrome",
      "abbreviation": null,
      "confidence": 0.95,
      "is_rare_disease": false,
      "category": null,
      "codes": {
        "icd10": "ICD10CM:Q77.6",
        "icd11": null,
        "snomed": null,
        "mondo": "MONDO:MONDO_0009162",
        "orpha": "Orphanet:289",
        "umls": "UMLS:C0013903",
        "mesh": "MESH:D004613"
      },
      "all_identifiers": [
        {
          "system": "MONDO",
          "code": "MONDO_0009162",
          "display": null
        },
        {
          "system": "DOID",
          "code": "DOID:12714",
          "display": null
        },
        {
          "system": "GARD",
          "code": "GARD:1301",
          "display": null
        },
        {
          "system": "ICD-10-CM",
          "code": "ICD10CM:Q77.6",
          "display": null
        },
        {
          "system": "ICD9",
          "code": "ICD9:756.55",
          "display": null
        },
        {
          "system": "MEDGEN",
          "code": "MEDGEN:8584",
          "display": null
        },
        {
          "system": "MeSH",
          "code": "MESH:D004613",
          "display": null
        },
        {
          "system": "MedDRA",
          "code": "MedDRA:10008724",
          "display": null
        },
        {
          "system": "NCIT",
          "code": "NCIT:C84684",
          "display": null
        },
        {
          "system": "NORD",
          "code": "NORD:1083",
          "display": null
        },
        {
          "system": "OMIM",
          "code": "OMIM:225500",
          "display": null
        },
        {
          "system": "Orphanet",
          "code": "Orphanet:289",
          "display": null
        },
        {
          "system": "SCTID",
          "code": "SCTID:62501005",
          "display": null
        },
        {
          "system": "UMLS",
          "code": "UMLS:C0013903",
          "display": null
        }
      ],
      "context": "Ellis-Van Creveld syndrome is a rare genetic disorder characterized by short limb dwarfism, additional fingers and/or toes (polydactyly), abnormal development of fingernails and, in over half of the cases, congenital heart defects. Motor development and intelligence are normal. This disorder is inherited as an autosomal rece",
      "page": 1,
      "mention_count": 2,
      "pages_mentioned": [
        1
      ],
      "lexicon_source": "2025_mondo_diseases.json",
      "validation_flags": [
        "lexicon_match",
        "pubtator_enriched",
        "deduplicated"
      ],
      "mesh_aliases": [],
      "pubtator_normalized_name": "Ellis-Van Creveld Syndrome",
      "enrichment_source": "pubtator3"
    },
    {
      "matched_text": "dwarfism",
      "preferred_label": "Schwartz-Jampel syndrome",
      "abbreviation": null,
      "confidence": 0.95,
      "is_rare_disease": true,
      "category": "rare_disease",
      "codes": {
        "icd10": null,
        "icd11": null,
        "snomed": null,
        "mondo": null,
        "orpha": "ORPHA:800",
        "umls": null,
        "mesh": "D010009"
      },
      "all_identifiers": [
        {
          "system": "ORPHA",
          "code": "ORPHA:800",
          "display": null
        },
        {
          "system": "MeSH",
          "code": "D010009",
          "display": "Osteochondrodysplasias"
        }
      ],
      "context": "Ellis-Van Creveld syndrome is a rare genetic disorder characterized by short limb dwarfism, additional fingers and/or toes (polydactyly), abnormal development of fingernails and, in over half of the cases, congenital heart defects. Motor development and intelligence are normal. This disorder is inherited as an autosomal recessive condition. Ellis-Van Creveld syndrome occurs in many ethni",
      "page": 1,
      "mention_count": 1,
      "pages_mentioned": [
        1
      ],
      "lexicon_source": "2025_08_orphanet_diseases.json",
      "validation_flags": [
        "lexicon_match",
        "pubtator_enriched",
        "deduplicated"
      ],
      "mesh_aliases": [
        "Stuve-Wiedemann syndrome"
      ],
      "pubtator_normalized_name": "Osteochondrodysplasias",
      "enrichment_source": "pubtator3"
    },
    {
      "matched_text": "congenital heart defects",
      "preferred_label": "congenital heart defects",
      "abbreviation": null,
      "confidence": 0.95,
      "is_rare_disease": false,
      "category": "cardiology",
      "codes": {
        "icd10": null,
        "icd11": null,
        "snomed": null,
        "mondo": "MONDO:MONDO_0005453",
        "orpha": null,
        "umls": "UMLS:C0152021",
        "mesh": "MESH:D006330"
      },
      "all_identifiers": [
        {
          "system": "MONDO",
          "code": "MONDO_0005453",
          "display": null
        },
        {
          "system": "DOID",
          "code": "DOID:1682",
          "display": null
        },
        {
          "system": "EFO",
          "code": "EFO:0005207",
          "display": null
        },
        {
          "system": "ICD9",
          "code": "ICD9:746.9",
          "display": null
        },
        {
          "system": "MEDGEN",
          "code": "MEDGEN:57501",
          "display": null
        },
        {
          "system": "MeSH",
          "code": "MESH:D006330",
          "display": null
        },
        {
          "system": "NCIT",
          "code": "NCIT:C95834",
          "display": null
        },
        {
          "system": "SCTID",
          "code": "SCTID:13213009",
          "display": null
        },
        {
          "system": "UMLS",
          "code": "UMLS:C0152021",
          "display": null
        },
        {
          "system": "icd11.foundation",
          "code": "icd11.foundation:2004408087",
          "display": null
        }
      ],
      "context": "Ellis-Van Creveld syndrome is a rare genetic disorder characterized by short limb dwarfism, additional fingers and/or toes (polydactyly), abnormal development of fingernails and, in over half of the cases, congenital heart defects. Motor development and intelligence are normal. This disorder is inherited as an autosomal recessive condition. Ellis-Van Creveld syndrome occurs in many ethnic groups throughout the world and effects males and females in equal numbers. This condition has been reported in approximately 150 individu",
      "page": 1,
      "mention_count": 1,
      "pages_mentioned": [
        1
      ],
      "lexicon_source": "2025_mondo_diseases.json",
      "validation_flags": [
        "lexicon_match",
        "pubtator_enriched",
        "deduplicated"
      ],
      "mesh_aliases": [
        "Heart defects limb shortening",
        "Deafness Congenital Heart Defects and Posterior Embryotoxon",
        "Noncompaction of Left Ventricular Myocardium with Congenital Heart Defects"
      ],
      "pubtator_normalized_name": "Heart Defects Congenital",
      "enrichment_source": "pubtator3"
    },
    {
      "matched_text": "genetic disorder",
      "preferred_label": "genetic disorder",
      "abbreviation": null,
      "confidence": 0.95,
      "is_rare_disease": false,
      "category": null,
      "codes": {
        "icd10": null,
        "icd11": null,
        "snomed": null,
        "mondo": "MONDO:MONDO_0003847",
        "orpha": null,
        "umls": "UMLS:C0019247",
        "mesh": "MESH:D030342"
      },
      "all_identifiers": [
        {
          "system": "MONDO",
          "code": "MONDO_0003847",
          "display": null
        },
        {
          "system": "DOID",
          "code": "DOID:630",
          "display": null
        },
        {
          "system": "EFO",
          "code": "EFO:0000508",
          "display": null
        },
        {
          "system": "ICD9",
          "code": "ICD9:799.89",
          "display": null
        },
        {
          "system": "MEDGEN",
          "code": "MEDGEN:5527",
          "display": null
        },
        {
          "system": "MeSH",
          "code": "MESH:D030342",
          "display": null
        },
        {
          "system": "NCIT",
          "code": "NCIT:C3101",
          "display": null
        },
        {
          "system": "SCTID",
          "code": "SCTID:32895009",
          "display": null
        },
        {
          "system": "UMLS",
          "code": "UMLS:C0019247",
          "display": null
        }
      ],
      "context": "Ellis-Van Creveld syndrome is a rare genetic disorder characterized by short limb dwarfism, additional fingers and/or toes (polydactyly), abnormal development of fingernails and, in over half of the cases, congenital heart defects. Motor development and intelligence are normal. This disorder is inherited as an autosomal recessive condition. Ellis-Van",
      "page": 1,
      "mention_count": 1,
      "pages_mentioned": [
        1
      ],
      "lexicon_source": "2025_mondo_diseases.json",
      "validation_flags": [
        "lexicon_match",
        "pubtator_enriched",
        "deduplicated"
      ],
      "mesh_aliases": [
        "Hemochromatosis"
      ],
      "pubtator_normalized_name": "Genetic Diseases Inborn",
      "enrichment_source": "pubtator3"
    },
    {
      "matched_text": "polydactyly",
      "preferred_label": "polydactyly",
      "abbreviation": null,
      "confidence": 0.95,
      "is_rare_disease": false,
      "category": null,
      "codes": {
        "icd10": "ICD10CM:Q69",
        "icd11": null,
        "snomed": null,
        "mondo": "MONDO:MONDO_0021003",
        "orpha": null,
        "umls": "UMLS:C0152427",
        "mesh": "MESH:D017689"
      },
      "all_identifiers": [
        {
          "system": "MONDO",
          "code": "MONDO_0021003",
          "display": null
        },
        {
          "system": "DOID",
          "code": "DOID:1148",
          "display": null
        },
        {
          "system": "HP",
          "code": "HP:0010442",
          "display": null
        },
        {
          "system": "ICD-10-CM",
          "code": "ICD10CM:Q69",
          "display": null
        },
        {
          "system": "ICD10WHO",
          "code": "ICD10WHO:Q69",
          "display": null
        },
        {
          "system": "ICD9",
          "code": "ICD9:755.00",
          "display": null
        },
        {
          "system": "MEDGEN",
          "code": "MEDGEN:57774",
          "display": null
        },
        {
          "system": "MeSH",
          "code": "MESH:D017689",
          "display": null
        },
        {
          "system": "MedDRA",
          "code": "MedDRA:10036063",
          "display": null
        },
        {
          "system": "NCIT",
          "code": "NCIT:C87110",
          "display": null
        },
        {
          "system": "OMIM",
          "code": "OMIM:603596",
          "display": null
        },
        {
          "system": "SCTID",
          "code": "SCTID:367506006",
          "display": null
        },
        {
          "system": "UMLS",
          "code": "UMLS:C0152427",
          "display": null
        }
      ],
      "context": "Ellis-Van Creveld syndrome is a rare genetic disorder characterized by short limb dwarfism, additional fingers and/or toes (polydactyly), abnormal development of fingernails and, in over half of the cases, congenital heart defects. Motor development and intelligence are normal. This disorder is inherited as an autosomal recessive condition. Ellis-Van Creveld syndrome occurs in many ethnic groups throughout the world and effects mal",
      "page": 1,
      "mention_count": 1,
      "pages_mentioned": [
        1
      ],
      "lexicon_source": "2025_mondo_diseases.json",
      "validation_flags": [
        "lexicon_match",
        "pubtator_enriched",
        "deduplicated"
      ],
      "mesh_aliases": [
        "Polydactyly",
        "Polydactyly Postaxial",
        "Orofaciodigital syndrome 6"
      ],
      "pubtator_normalized_name": "Polydactyly Preaxial III",
      "enrichment_source": "pubtator3"
    },
    {
      "matched_text": "natal teeth",
      "preferred_label": "Natal teeth",
      "abbreviation": null,
      "confidence": 0.95,
      "is_rare_disease": false,
      "category": null,
      "codes": {
        "icd10": null,
        "icd11": null,
        "snomed": null,
        "mondo": "MONDO:MONDO_0008532",
        "orpha": null,
        "umls": "UMLS:C0027443",
        "mesh": "C537487"
      },
      "all_identifiers": [
        {
          "system": "MONDO",
          "code": "MONDO_0008532",
          "display": null
        },
        {
          "system": "HP",
          "code": "HP:0000695",
          "display": null
        },
        {
          "system": "MEDGEN",
          "code": "MEDGEN:10268",
          "display": null
        },
        {
          "system": "OMIM",
          "code": "OMIM:187050",
          "display": null
        },
        {
          "system": "SCTID",
          "code": "SCTID:21995002",
          "display": null
        },
        {
          "system": "UMLS",
          "code": "UMLS:C0027443",
          "display": null
        },
        {
          "system": "MeSH",
          "code": "C537487",
          "display": "Steatocystoma multiplex with natal teeth"
        }
      ],
      "context": "the Old Order Amish population of Lancaster County, Pennsylvania and in the native population of Western Australia. Ellis-Van-Creveld syndrome is diagnosed by the observation of short stature, slow growth, skeletal abnormalities determined by imaging techniques and sometimes teeth present at birth (natal teeth). Molecular genetic testing for the EVC and EVC2 genes is available on a research basis only. Prenatal diagnosis is possible by ultrasound.",
      "page": 1,
      "mention_count": 2,
      "pages_mentioned": [
        1
      ],
      "lexicon_source": "2025_mondo_diseases.json",
      "validation_flags": [
        "lexicon_match",
        "pubtator_enriched",
        "deduplicated"
      ],
      "mesh_aliases": [
        "Ectodermal Dysplasia with Natal Teeth Turnpenny Type"
      ],
      "pubtator_normalized_name": "Steatocystoma multiplex with natal teeth",
      "enrichment_source": "pubtator3"
    },
    {
      "matched_text": "stature",
      "preferred_label": "stature",
      "abbreviation": null,
      "confidence": 0.95,
      "is_rare_disease": false,
      "category": null,
      "codes": {
        "icd10": null,
        "icd11": null,
        "snomed": null,
        "mondo": "MONDO:MONDO_0044267",
        "orpha": null,
        "umls": null,
        "mesh": "C537327"
      },
      "all_identifiers": [
        {
          "system": "MONDO",
          "code": "MONDO_0044267",
          "display": null
        },
        {
          "system": "HGNC",
          "code": "HGNC:4211",
          "display": null
        },
        {
          "system": "MeSH",
          "code": "C537327",
          "display": "SHORT syndrome"
        }
      ],
      "context": "d females in equal numbers. This condition has been reported in approximately 150 individuals. It is more common in the Old Order Amish population of Lancaster County, Pennsylvania and in the native population of Western Australia. Ellis-Van-Creveld syndrome is diagnosed by the observation of short stature, slow growth, skeletal abnormalities determined by imaging techniques and sometimes teeth present at birth (natal teeth). Molecular genetic testing for the EVC and EVC2 genes is available on a research basis only. Prenatal diagnosis is possible by ultrasound.",
      "page": 1,
      "mention_count": 1,
      "pages_mentioned": [
        1
      ],
      "lexicon_source": "2025_mondo_diseases.json",
      "validation_flags": [
        "lexicon_match",
        "pubtator_enriched",
        "deduplicated"
      ],
      "mesh_aliases": [
        "Corneodermatoosseous syndrome",
        "Trichothiodystrophy Syndromes",
        "Miller-McKusick-Malvaux-Syndrome (3M Syndrome)"
      ],
      "pubtator_normalized_name": "SHORT syndrome",
      "enrichment_source": "pubtator3"
    }
  ]
}