{
  "run_id": "RUN_20260204_234342_996d5a3920e1",
  "timestamp": "2026-02-05T04:50:00.032040",
  "document": "Congenital-Central-Hypoventilation-Syndrome.pdf",
  "document_path": "/Users/frederictetard/Projects/ese/gold_data/NLP4RARE/train/Congenital-Central-Hypoventilation-Syndrome.pdf",
  "pipeline_version": "0.8",
  "total_candidates": 1,
  "total_validated": 1,
  "total_rejected": 0,
  "total_ambiguous": 0,
  "diseases": [
    {
      "matched_text": "CCHS",
      "preferred_label": "Congenital central hypoventilation syndrome",
      "abbreviation": "CCHS",
      "confidence": 0.95,
      "is_rare_disease": true,
      "category": "rare_disease",
      "codes": {
        "icd10": "G47.3",
        "icd11": "7A42.1",
        "snomed": null,
        "mondo": null,
        "orpha": "ORPHA:661",
        "umls": null,
        "mesh": "C536209"
      },
      "all_identifiers": [
        {
          "system": "ORPHA",
          "code": "ORPHA:661",
          "display": null
        },
        {
          "system": "ICD-10",
          "code": "G47.3",
          "display": null
        },
        {
          "system": "ICD-11",
          "code": "7A42.1",
          "display": null
        },
        {
          "system": "MeSH",
          "code": "C536209",
          "display": "Congenital central hypoventilation syndrome"
        }
      ],
      "context": "CCHS is a rare disorder that affects females and males in equal numbers. Though the mutation is already present before birth, in milder cases the diagnosis may be missed until after the newborn period. Some affected individuals will not be identified until after receiving sedation, anesthesia, or anti-s",
      "page": 1,
      "mention_count": 1,
      "pages_mentioned": [
        1
      ],
      "lexicon_source": "2025_08_rare_disease_acronyms.json",
      "validation_flags": [
        "lexicon_match",
        "pubtator_enriched",
        "deduplicated"
      ],
      "mesh_aliases": [],
      "pubtator_normalized_name": "Congenital central hypoventilation syndrome",
      "enrichment_source": "pubtator3"
    }
  ]
}