{
  "doc_id": "Aniridia",
  "doc_filename": "Aniridia.pdf",
  "top_entities": [
    {
      "name": "aniridia",
      "mention_count": 1,
      "entity_type": "disease"
    }
  ],
  "file_size_bytes": 1545,
  "file_size_human": "1.5 KB",
  "file_extension": ".pdf",
  "pdf_title": "(anonymous)",
  "pdf_author": "(anonymous)",
  "pdf_page_count": 1,
  "pdf_creation_date": "2026-01-07T22:25:18",
  "doi": null,
  "doi_url": null,
  "document_type_code": "DLA",
  "document_type_name": "Disease Landscape Analysis",
  "document_type_group": "Disease Landscape Analysis",
  "classification_confidence": 0.85,
  "title": "Aniridia: Epidemiology and Demographics",
  "short_description": "Clinical document describing the prevalence and demographic distribution of aniridia, a rare eye disorder.",
  "long_description": "This clinical research document provides epidemiological information about aniridia, a rare congenital eye condition characterized by the absence or underdevelopment of the iris. The document presents key demographic data indicating that aniridia affects males and females equally, with no gender predisposition. It establishes the disorder's rarity by citing prevalence estimates of approximately 1 in 60,000 to 100,000 live births in the United States, providing important baseline data for understanding the scope and impact of this genetic condition.",
  "document_date": "2026-01-07T22:25:18",
  "document_date_source": "pdf_metadata",
  "extraction_timestamp": "2026-02-05T02:43:55.597020"
}